{
  "main": {
    "id": "86abfd4469eb4163",
    "type": "split",
    "children": [
      {
        "id": "ec744f4ed84bc5f7",
        "type": "tabs",
        "children": [
          {
            "id": "9f39b580af0c2913",
            "type": "leaf",
            "state": {
              "type": "markdown",
              "state": {
                "file": "POSIX.md",
                "mode": "source",
                "source": false
              }
            }
          },
          {
            "id": "d7af27ed6dcde2bb",
            "type": "leaf",
            "state": {
              "type": "markdown",
              "state": {
                "file": "BIOS.md",
                "mode": "source",
                "source": false
              }
            }
          },
          {
            "id": "9cf2c60c50e2fe4a",
            "type": "leaf",
            "state": {
              "type": "markdown",
              "state": {
                "file": "lscpu.md",
                "mode": "source",
                "source": false
              }
            }
          },
          {
            "id": "265c00f45871a15d",
            "type": "leaf",
            "state": {
              "type": "markdown",
              "state": {
                "file": "x86 architecture.md",
                "mode": "source",
                "source": false
              }
            }
          },
          {
            "id": "7a99b584f0bf880a",
            "type": "leaf",
            "state": {
              "type": "markdown",
              "state": {
                "file": "RISC.md",
                "mode": "source",
                "source": false
              }
            }
          },
          {
            "id": "574a2f63e42e9b72",
            "type": "leaf",
            "state": {
              "type": "markdown",
              "state": {
                "file": "Linux Kernel.md",
                "mode": "source",
                "backlinks": true,
                "source": false
              }
            }
          },
          {
            "id": "73052544a2f07eec",
            "type": "leaf",
            "state": {
              "type": "markdown",
              "state": {
                "file": "Device Drivers.md",
                "mode": "source",
                "source": false
              }
            }
          },
          {
            "id": "6f975c18d4682788",
            "type": "leaf",
            "state": {
              "type": "markdown",
              "state": {
                "file": "syscalls.md",
                "mode": "source",
                "source": false
              }
            }
          },
          {
            "id": "bb578b4c665c910b",
            "type": "leaf",
            "state": {
              "type": "markdown",
              "state": {
                "file": "modules.md",
                "mode": "source",
                "source": false
              }
            }
          }
        ],
        "currentTab": 8
      }
    ],
    "direction": "vertical"
  },
  "left": {
    "id": "6d4811da9c9c6339",
    "type": "split",
    "children": [
      {
        "id": "a0430985ff27f99e",
        "type": "tabs",
        "children": [
          {
            "id": "a7b7e10ec6b1174d",
            "type": "leaf",
            "state": {
              "type": "file-explorer",
              "state": {
                "sortOrder": "alphabetical"
              }
            }
          },
          {
            "id": "2b5267d04ebec949",
            "type": "leaf",
            "state": {
              "type": "search",
              "state": {
                "query": "",
                "matchingCase": false,
                "explainSearch": false,
                "collapseAll": false,
                "extraContext": false,
                "sortOrder": "alphabetical"
              }
            }
          },
          {
            "id": "6df7d8aa945bb13e",
            "type": "leaf",
            "state": {
              "type": "bookmarks",
              "state": {}
            }
          }
        ]
      }
    ],
    "direction": "horizontal",
    "width": 300
  },
  "right": {
    "id": "a744756ca0b2f2ba",
    "type": "split",
    "children": [
      {
        "id": "707ddfdd928402b5",
        "type": "tabs",
        "children": [
          {
            "id": "bed9a21de97da141",
            "type": "leaf",
            "state": {
              "type": "backlink",
              "state": {
                "file": "modules.md",
                "collapseAll": false,
                "extraContext": false,
                "sortOrder": "alphabetical",
                "showSearch": false,
                "searchQuery": "",
                "backlinkCollapsed": false,
                "unlinkedCollapsed": true
              }
            }
          },
          {
            "id": "3303e180e1464910",
            "type": "leaf",
            "state": {
              "type": "outgoing-link",
              "state": {
                "file": "modules.md",
                "linksCollapsed": false,
                "unlinkedCollapsed": true
              }
            }
          },
          {
            "id": "5087a3ca4c046618",
            "type": "leaf",
            "state": {
              "type": "tag",
              "state": {
                "sortOrder": "frequency",
                "useHierarchy": true
              }
            }
          },
          {
            "id": "65abd2594d445f7f",
            "type": "leaf",
            "state": {
              "type": "outline",
              "state": {
                "file": "modules.md"
              }
            }
          }
        ]
      }
    ],
    "direction": "horizontal",
    "width": 300,
    "collapsed": true
  },
  "left-ribbon": {
    "hiddenItems": {
      "switcher:Open quick switcher": false,
      "graph:Open graph view": false,
      "canvas:Create new canvas": false,
      "daily-notes:Open today's daily note": false,
      "templates:Insert template": false,
      "command-palette:Open command palette": false,
      "templater-obsidian:Templater": false
    }
  },
  "active": "bb578b4c665c910b",
  "lastOpenFiles": [
    "syscalls.md",
    "modules.md",
    "Pasted image 20240717144441.png",
    "strace.md",
    "zleelb/git/HEAD.md",
    "Pasted image 20240717143201.png",
    "zleelb/imgs/Pasted image 20240717142512.png",
    "x86 architecture.md",
    "zleelb/git/git push.md",
    "fscanf.md",
    "Device Drivers.md",
    "Linux Kernel.md",
    "Linux filesystems.md",
    "Linux networking.md",
    "Linux memory management.md",
    "zleelb/imgs/Pasted image 20240717135554.png",
    "Linux process management.md",
    "ps.md",
    "RISC.md",
    "lscpu.md",
    "BIOS.md",
    "POSIX.md",
    "zleelb/Hubs/linux.md",
    "zleelb/Templates/Basic note template linux.md",
    "zleelb/git/git branch.md",
    "zleelb/git/git pull.md",
    "zleelb/git/Pull Requests.md",
    "zleelb/git/upstream branch.md",
    "Errno.md",
    "zleelb/git/git restore.md",
    "4913"
  ]
}